README.rst
setup.py
djehuty_tiqav/__init__.py
djehuty_tiqav/commands.py
djehuty_tiqav.egg-info/PKG-INFO
djehuty_tiqav.egg-info/SOURCES.txt
djehuty_tiqav.egg-info/dependency_links.txt
djehuty_tiqav.egg-info/entry_points.txt
djehuty_tiqav.egg-info/not-zip-safe
djehuty_tiqav.egg-info/requires.txt
djehuty_tiqav.egg-info/top_level.txt